{"return_1d": -0.014033, "return_5d": 0.058594, "return_20d": -0.025681, "return_60d": -0.022165, "return_252d": -0.305764, "sma_20": 38.031, "sma_50": 39.1168, "sma_200": 44.34005, "price_vs_sma20": -0.002393, "price_vs_sma50": -0.030084, "price_vs_sma200": -0.14434, "volatility_20d": 0.389779, "volatility_60d": 0.282493, "drawdown": -0.405702, "max_drawdown_1y": -0.447368, "volume_ratio": 0.963221, "rsi_14": 47.903848, "macd": -0.540525, "macd_signal": -0.71116, "macd_histogram": 0.170635, "bb_width": 0.169282, "bb_position": 0.485831, "stoch_k": 71.206897, "stoch_d": 68.766669, "adx": 29.241918, "atr_14": 1.174498, "last_close": 37.94, "last_date": "2026-03-04"}