{"return_1d": -0.003315, "return_5d": -0.042753, "return_20d": 0.037975, "return_60d": 0.05021, "return_252d": 0.158298, "sma_20": 63.553, "sma_50": 61.072, "sma_200": 58.74758, "price_vs_sma20": -0.006499, "price_vs_sma50": 0.033862, "price_vs_sma200": 0.074768, "volatility_20d": 0.21153, "volatility_60d": 0.196964, "drawdown": -0.147149, "max_drawdown_1y": -0.352091, "volume_ratio": 1.242022, "rsi_14": 51.075509, "macd": 0.846071, "macd_signal": 1.140903, "macd_histogram": -0.294832, "bb_width": 0.11172, "bb_position": 0.441452, "stoch_k": 25.546218, "stoch_d": 29.131653, "adx": 26.307042, "atr_14": 1.330744, "last_close": 63.14, "last_date": "2026-02-27"}