{"return_1d": -0.03864, "return_5d": -0.03199, "return_20d": -0.126541, "return_60d": -0.290944, "return_252d": -0.012437, "sma_20": 118.04475, "sma_50": 126.9817, "sma_200": 138.80425, "price_vs_sma20": -0.051546, "price_vs_sma50": -0.118298, "price_vs_sma200": -0.193396, "volatility_20d": 0.868809, "volatility_60d": 0.616592, "drawdown": -0.439415, "max_drawdown_1y": -0.557387, "volume_ratio": 0.677458, "rsi_14": 42.753369, "macd": -4.928197, "macd_signal": -4.561524, "macd_histogram": -0.366673, "bb_width": 0.293307, "bb_position": 0.314708, "stoch_k": 39.373412, "stoch_d": 42.073572, "adx": 19.344457, "atr_14": 7.777975, "last_close": 111.96, "last_date": "2026-02-27"}