{"return_1d": -0.010195, "return_5d": -0.089432, "return_20d": -0.040586, "return_60d": 0.129766, "return_252d": -0.207665, "sma_20": 115.8655, "sma_50": 108.6088, "sma_200": 104.2293, "price_vs_sma20": -0.061498, "price_vs_sma50": 0.001208, "price_vs_sma200": 0.043277, "volatility_20d": 0.27197, "volatility_60d": 0.506451, "drawdown": -0.512617, "max_drawdown_1y": -0.643494, "volume_ratio": 0.740689, "rsi_14": 41.591559, "macd": 1.560977, "macd_signal": 3.038133, "macd_histogram": -1.477156, "bb_width": 0.118821, "bb_position": -0.051483, "stoch_k": 12.637008, "stoch_d": 17.402069, "adx": 32.204385, "atr_14": 4.130706, "last_close": 108.74, "last_date": "2026-03-04"}