{"return_1d": -0.011475, "return_5d": 0.015428, "return_20d": 0.137998, "return_60d": 0.159241, "return_252d": -0.055502, "sma_20": 545.379, "sma_50": 521.584156, "sma_200": 541.384616, "price_vs_sma20": 0.033043, "price_vs_sma50": 0.080171, "price_vs_sma200": 0.040665, "volatility_20d": 0.371222, "volatility_60d": 0.304858, "drawdown": -0.159985, "max_drawdown_1y": -0.339363, "volume_ratio": 0.96233, "rsi_14": 59.4734, "macd": 11.738123, "macd_signal": 11.733867, "macd_histogram": 0.004256, "bb_width": 0.142216, "bb_position": 0.724913, "stoch_k": 73.429952, "stoch_d": 68.975532, "adx": 25.039214, "atr_14": 19.120615, "last_close": 563.4, "last_date": "2026-03-02"}