{"return_1d": -0.025091, "return_5d": -0.023084, "return_20d": -0.132444, "return_60d": 0.000277, "return_252d": -0.046245, "sma_20": 661.61025, "sma_50": 656.5437, "sma_200": 690.550156, "price_vs_sma20": -0.03187, "price_vs_sma50": -0.024399, "price_vs_sma200": -0.072442, "volatility_20d": 0.277105, "volatility_60d": 0.347114, "drawdown": -0.188, "max_drawdown_1y": -0.341508, "volume_ratio": 0.498939, "rsi_14": 44.778046, "macd": -4.219621, "macd_signal": -2.3992, "macd_histogram": -1.820421, "bb_width": 0.138388, "bb_position": 0.262127, "stoch_k": 22.434735, "stoch_d": 40.352308, "adx": 13.000166, "atr_14": 19.30193, "last_close": 640.525, "last_date": "2026-02-27"}