{"return_1d": 0.032896, "return_5d": 0.15119, "return_20d": 0.211537, "return_60d": -0.271605, "return_252d": -0.321133, "sma_20": 107.671, "sma_50": 124.3654, "sma_200": 169.40047, "price_vs_sma20": 0.154814, "price_vs_sma50": -0.000204, "price_vs_sma200": -0.266, "volatility_20d": 0.464771, "volatility_60d": 0.521803, "drawdown": -0.46881, "max_drawdown_1y": -0.570314, "volume_ratio": 1.189455, "rsi_14": 62.100384, "macd": -1.484571, "macd_signal": -4.913887, "macd_histogram": 3.429316, "bb_width": 0.196785, "bb_position": 1.181252, "stoch_k": 98.744113, "stoch_d": 94.299608, "adx": 29.676313, "atr_14": 5.554338, "last_close": 124.34, "last_date": "2026-03-06"}