{"return_1d": -0.000825, "return_5d": 0.025388, "return_20d": 0.143801, "return_60d": 0.29038, "return_252d": 0.668748, "sma_20": 17.271, "sma_50": 15.6672, "sma_200": 13.888486, "price_vs_sma20": 0.052342, "price_vs_sma50": 0.160067, "price_vs_sma200": 0.308638, "volatility_20d": 0.361946, "volatility_60d": 0.263824, "drawdown": -0.000825, "max_drawdown_1y": -0.089746, "volume_ratio": 0.062441, "rsi_14": 70.806254, "macd": 0.726385, "macd_signal": 0.718018, "macd_histogram": 0.008367, "bb_width": 0.149142, "bb_position": 0.833499, "stoch_k": 96.986301, "stoch_d": 91.349088, "adx": 57.514267, "atr_14": 0.4161, "last_close": 18.175, "last_date": "2026-03-02"}