{"return_1d": -0.014399, "return_5d": -0.006769, "return_20d": -0.027064, "return_60d": -0.002489, "return_252d": 0.112896, "sma_20": 258.571915, "sma_50": 254.329614, "sma_200": 259.583879, "price_vs_sma20": -0.012576, "price_vs_sma50": 0.003894, "price_vs_sma200": -0.016426, "volatility_20d": 0.341835, "volatility_60d": 0.26939, "drawdown": -0.126681, "max_drawdown_1y": -0.290743, "volume_ratio": 0.766014, "rsi_14": 48.463198, "macd": 0.236695, "macd_signal": 0.488382, "macd_histogram": -0.251687, "bb_width": 0.10153, "bb_position": 0.374554, "stoch_k": 57.080201, "stoch_d": 71.548929, "adx": 10.251214, "atr_14": 6.890232, "last_close": 255.32, "last_date": "2026-03-05"}