{"return_1d": 0.016124, "return_5d": -0.054706, "return_20d": 0.043506, "return_60d": 0.090231, "return_252d": 0.362218, "sma_20": 331.095, "sma_50": 318.162, "sma_200": 294.7565, "price_vs_sma20": -0.029282, "price_vs_sma50": 0.010177, "price_vs_sma200": 0.090392, "volatility_20d": 0.41884, "volatility_60d": 0.298792, "drawdown": -0.074309, "max_drawdown_1y": -0.230917, "volume_ratio": 0.060886, "rsi_14": 46.869532, "macd": 3.058197, "macd_signal": 6.236295, "macd_histogram": -3.178099, "bb_width": 0.177746, "bb_position": 0.330292, "stoch_k": 19.452055, "stoch_d": 16.929402, "adx": 25.887645, "atr_14": 8.853891, "last_close": 321.4, "last_date": "2026-03-06"}