{"return_1d": 0.032757, "return_5d": -0.005387, "return_20d": 0.056958, "return_60d": 0.052474, "return_252d": -0.059993, "sma_20": 192.16025, "sma_50": 190.2163, "sma_200": 204.853788, "price_vs_sma20": 0.03281, "price_vs_sma50": 0.043365, "price_vs_sma200": -0.031187, "volatility_20d": 0.331786, "volatility_60d": 0.254429, "drawdown": -0.456948, "max_drawdown_1y": -0.508431, "volume_ratio": 1.283126, "rsi_14": 56.579715, "macd": 2.816801, "macd_signal": 2.545788, "macd_histogram": 0.271013, "bb_width": 0.162792, "bb_position": 0.695143, "stoch_k": 76.619244, "stoch_d": 67.616652, "adx": 19.526653, "atr_14": 5.166394, "last_close": 198.465, "last_date": "2026-02-27"}