{"return_1d": 0.002771, "return_5d": 0.023717, "return_20d": 0.003767, "return_60d": -0.078619, "return_252d": -0.128051, "sma_20": 424.82881, "sma_50": 484.669524, "sma_200": 504.99008, "price_vs_sma20": 0.064805, "price_vs_sma50": -0.066663, "price_vs_sma200": -0.10422, "volatility_20d": 0.465604, "volatility_60d": 0.398874, "drawdown": -0.193309, "max_drawdown_1y": -0.304776, "volume_ratio": 0.498301, "rsi_14": 51.60856, "macd": -8.852363, "macd_signal": -16.449976, "macd_histogram": 7.597613, "bb_width": 0.169884, "bb_position": 0.858251, "stoch_k": 99.378517, "stoch_d": 97.190267, "adx": 36.813135, "atr_14": 13.591604, "last_close": 452.36, "last_date": "2026-03-06"}