{"return_1d": -0.004042, "return_5d": 0.01145, "return_20d": 0.134615, "return_60d": 0.371091, "return_252d": -0.068496, "sma_20": 46.66241, "sma_50": 42.950974, "sma_200": 42.072251, "price_vs_sma20": 0.003377, "price_vs_sma50": 0.09008, "price_vs_sma200": 0.112848, "volatility_20d": 0.58059, "volatility_60d": 0.437021, "drawdown": -0.143147, "max_drawdown_1y": -0.405171, "volume_ratio": 0.730415, "rsi_14": 54.646592, "macd": 1.254799, "macd_signal": 1.714632, "macd_histogram": -0.459833, "bb_width": 0.278372, "bb_position": 0.512091, "stoch_k": 36.814023, "stoch_d": 39.548923, "adx": 28.53512, "atr_14": 1.930964, "last_close": 46.82, "last_date": "2026-03-02"}