{"return_1d": -0.001438, "return_5d": 0.013003, "return_20d": 0.066535, "return_60d": 0.067317, "return_252d": 0.295752, "sma_20": 156.163105, "sma_50": 154.799794, "sma_200": 140.530363, "price_vs_sma20": 0.022713, "price_vs_sma50": 0.03172, "price_vs_sma200": 0.13648, "volatility_20d": 0.194483, "volatility_60d": 0.169172, "drawdown": -0.012062, "max_drawdown_1y": -0.110448, "volume_ratio": 0.927296, "rsi_14": 59.739705, "macd": 1.761435, "macd_signal": 1.271928, "macd_histogram": 0.489507, "bb_width": 0.069902, "bb_position": 0.817709, "stoch_k": 76.857624, "stoch_d": 82.519844, "adx": 21.672818, "atr_14": 3.283986, "last_close": 159.71, "last_date": "2026-03-03"}