{"return_1d": -0.00638, "return_5d": -0.00161, "return_20d": 0.119365, "return_60d": 0.019396, "return_252d": 0.39768, "sma_20": 201.570965, "sma_50": 192.234798, "sma_200": 174.003368, "price_vs_sma20": 0.027529, "price_vs_sma50": 0.077432, "price_vs_sma200": 0.190322, "volatility_20d": 0.247631, "volatility_60d": 0.213607, "drawdown": -0.035387, "max_drawdown_1y": -0.129861, "volume_ratio": 1.826551, "rsi_14": 63.759765, "macd": 5.308358, "macd_signal": 5.251911, "macd_histogram": 0.056447, "bb_width": 0.180181, "bb_position": 0.648692, "stoch_k": 57.965161, "stoch_d": 68.157599, "adx": 31.772798, "atr_14": 4.272636, "last_close": 207.12, "last_date": "2026-02-27"}