[{"ticker": "DG.PA", "signalPrimary": "Bearish divergence", "signalSecondary": "Price up but momentum indicators negative", "explanation": "Price has gained 8.8% over 20 days but RSI (49) and MACD are negative, suggesting the rally may stall.", "horizon": "short", "name": "Vinci SA", "detectedAt": "2026-03-05"}, {"ticker": "SAF.PA", "signalPrimary": "Bearish divergence", "signalSecondary": "Price up but momentum indicators negative", "explanation": "Price has gained 7.4% over 20 days but RSI (48) and MACD are negative, suggesting the rally may stall.", "horizon": "short", "name": "Safran SA", "detectedAt": "2026-03-05"}, {"ticker": "BDX", "signalPrimary": "Bearish divergence", "signalSecondary": "Price up but momentum indicators negative", "explanation": "Price has gained 5.6% over 20 days but RSI (48) and MACD are negative, suggesting the rally may stall.", "horizon": "short", "name": "Becton Dickinson", "detectedAt": "2026-03-04"}, {"ticker": "CPAY", "signalPrimary": "Bearish divergence", "signalSecondary": "Price up but momentum indicators negative", "explanation": "Price has gained 12.5% over 20 days but RSI (49) and MACD are negative, suggesting the rally may stall.", "horizon": "short", "name": "Corpay", "detectedAt": "2026-03-04"}, {"ticker": "MAR", "signalPrimary": "Bearish divergence", "signalSecondary": "Price up but momentum indicators negative", "explanation": "Price has gained 5.7% over 20 days but RSI (49) and MACD are negative, suggesting the rally may stall.", "horizon": "short", "name": "Marriott International", "detectedAt": "2026-03-04"}, {"ticker": "NRG", "signalPrimary": "Bearish divergence", "signalSecondary": "Price up but momentum indicators negative", "explanation": "Price has gained 7.5% over 20 days but RSI (47) and MACD are negative, suggesting the rally may stall.", "horizon": "short", "name": "NRG Energy", "detectedAt": "2026-03-04"}, {"ticker": "ON", "signalPrimary": "Bearish divergence", "signalSecondary": "Price up but momentum indicators negative", "explanation": "Price has gained 5.2% over 20 days but RSI (41) and MACD are negative, suggesting the rally may stall.", "horizon": "short", "name": "ON Semiconductor", "detectedAt": "2026-03-04"}, {"ticker": "SW", "signalPrimary": "Bearish divergence", "signalSecondary": "Price up but momentum indicators negative", "explanation": "Price has gained 11.5% over 20 days but RSI (48) and MACD are negative, suggesting the rally may stall.", "horizon": "short", "name": "Smurfit Westrock", "detectedAt": "2026-03-04"}, {"ticker": "URI", "signalPrimary": "Bearish divergence", "signalSecondary": "Price up but momentum indicators negative", "explanation": "Price has gained 7.7% over 20 days but RSI (48) and MACD are negative, suggesting the rally may stall.", "horizon": "short", "name": "United Rentals", "detectedAt": "2026-03-04"}, {"ticker": "VTRS", "signalPrimary": "Bearish divergence", "signalSecondary": "Price up but momentum indicators negative", "explanation": "Price has gained 7.5% over 20 days but RSI (48) and MACD are negative, suggesting the rally may stall.", "horizon": "short", "name": "Viatris", "detectedAt": "2026-03-04"}, {"ticker": "VST", "signalPrimary": "Bearish divergence", "signalSecondary": "Price up but momentum indicators negative", "explanation": "Price has gained 6.8% over 20 days but RSI (47) and MACD are negative, suggesting the rally may stall.", "horizon": "short", "name": "Vistra Corp.", "detectedAt": "2026-03-04"}, {"ticker": "AMZN", "signalPrimary": "Bullish divergence", "signalSecondary": "Price down but momentum indicators positive", "explanation": "Price has dropped 9.1% over 20 days but RSI (52) and MACD remain positive, suggesting the decline may be temporary.", "horizon": "short", "name": "Amazon", "detectedAt": "2026-03-04"}]